nexosapi/__init__.py
nexosapi/api/__init__.py
nexosapi/api/controller.py
nexosapi/api/controller.pyi
nexosapi/api/endpoints/__init__.py
nexosapi/api/endpoints/__init__.pyi
nexosapi/api/endpoints/audio/__init__.py
nexosapi/api/endpoints/chat/__init__.py
nexosapi/api/endpoints/chat/completions.py
nexosapi/api/endpoints/chat/completions.pyi
nexosapi/api/endpoints/images/__init__.py
nexosapi/common/__init__.py
nexosapi/common/exceptions.py
nexosapi/common/logging.py
nexosapi/config/__init__.py
nexosapi/config/settings/__init__.py
nexosapi/config/settings/defaults.py
nexosapi/config/settings/services.py
nexosapi/config/setup.py
nexosapi/domain/__init__.py
nexosapi/domain/base.py
nexosapi/domain/data.py
nexosapi/domain/headers.py
nexosapi/domain/metadata.py
nexosapi/domain/requests.py
nexosapi/domain/responses.py
nexosapi/services/__init__.py
nexosapi/services/http.py
nexosapi-0.1.0.dist-info/LICENSE
nexosapi-0.1.0.dist-info/METADATA
nexosapi-0.1.0.dist-info/WHEEL
nexosapi-0.1.0.dist-info/RECORD
