Metadata-Version: 2.3
Name: nexosapi
Version: 0.1.0
Summary: SDK for Nexos API
Author: Kamil Rybacki
Author-email: kamilandrzejrybacki@gmail.com
Requires-Python: >=3.12
Classifier: Programming Language :: Python :: 3
Classifier: Programming Language :: Python :: 3.12
Classifier: Programming Language :: Python :: 3.13
Requires-Dist: dependency-injector (>=4.48.1,<5.0.0)
Requires-Dist: environ-config (>=24.1.0,<25.0.0)
Requires-Dist: httpx (>=0.28.1,<0.29.0)
Requires-Dist: tenacity (>=9.1.2,<10.0.0)
